[ {
  "CaseEventID" : "c100ResSolAllegationsOfHarmB",
  "CaseFieldID" : "respChildPsychologicalAbuse",
  "ListElementCode" : "respAbuseNatureDescription",
  "CaseTypeID" : "PRLAPPS"
}, {
  "CaseEventID" : "c100ResSolAllegationsOfHarmB",
  "CaseFieldID" : "respChildPsychologicalAbuse",
  "ListElementCode" : "respBehavioursStartDateAndLength",
  "CaseTypeID" : "PRLAPPS"
}, {
  "CaseEventID" : "c100ResSolAllegationsOfHarmB",
  "CaseFieldID" : "respChildPsychologicalAbuse",
  "ListElementCode" : "respBehavioursApplicantSoughtHelp",
  "CaseTypeID" : "PRLAPPS"
}, {
  "CaseEventID" : "c100ResSolAllegationsOfHarmB",
  "CaseFieldID" : "respChildPsychologicalAbuse",
  "ListElementCode" : "respBehavioursApplicantHelpSoughtWho",
  "CaseTypeID" : "PRLAPPS"
} ]